{"stats":{"minecraft:custom":{"minecraft:time_since_rest":8634,"minecraft:interact_with_smithing_table":1,"minecraft:sprint_one_cm":61074,"minecraft:damage_taken":458,"minecraft:walk_one_cm":101758,"minecraft:mob_kills":1,"vampirism:interact_with_coffin":2,"minecraft:drop":8,"minecraft:damage_dealt":200,"minecraft:swim_one_cm":686,"minecraft:talked_to_villager":2,"minecraft:interact_with_crafting_table":4,"minecraft:fly_one_cm":217172,"minecraft:open_chest":8,"minecraft:crouch_one_cm":278,"minecraft:play_time":52557,"minecraft:deaths":1,"minecraft:sneak_time":1327,"minecraft:walk_under_water_one_cm":1443,"minecraft:jump":292,"minecraft:leave_game":2,"minecraft:walk_on_water_one_cm":2584,"minecraft:time_since_death":36255,"minecraft:sleep_in_bed":3,"minecraft:total_world_time":52557,"minecraft:fall_one_cm":5706},"minecraft:killed":{"minecraft:zombie":1},"minecraft:killed_by":{"minecraft:zombie":1},"minecraft:mined":{"minecraft:smithing_table":1,"minecraft:large_fern":2,"minecraft:sweet_berry_bush":7,"werewolves:wolfsbane":8,"minecraft:spruce_log":1,"treechop:chopped_log":5,"minecraft:grass":2,"minecraft:grass_block":1,"minecraft:oak_log":1,"minecraft:sand":4,"minecraft:gravel":4,"minecraft:dirt":2,"minecraft:spruce_leaves":4,"minecraft:stone":42,"minecraft:sugar_cane":3,"minecraft:oak_leaves":11},"minecraft:picked_up":{"minecraft:stick":15,"minecraft:allium":1,"minecraft:clay_ball":5,"minecraft:sweet_berries":13,"minecraft:smithing_table":1,"minecraft:gravel":4,"minecraft:sand":4,"werewolves:wolfsbane":8,"minecraft:oak_log":29,"vampirism:vampire_fang":1,"minecraft:spruce_log":1,"minecraft:dirt":3,"minecraft:item_frame":1,"minecraft:apple":1,"minecraft:rotten_flesh":5,"minecraft:bread":2,"minecraft:oak_sapling":7,"minecraft:sugar_cane":10,"minecraft:cobblestone":42,"vampirism:coffin_white":1},"minecraft:used":{"minecraft:iron_shovel":4,"minecraft:iron_axe":39,"minecraft:bread":2,"minecraft:iron_helmet":2,"minecraft:wooden_pickaxe":49,"minecraft:zombie_spawn_egg":1,"minecraft:gravel":4,"cataclysm:wrath_of_the_desert":1,"minecraft:iron_chestplate":2,"minecraft:dirt":3,"minecraft:crafting_table":1,"vampirism:coffin_white":1,"minecraft:sweet_berries":6,"minecraft:furnace":3,"minecraft:pumpkin_pie":1},"minecraft:crafted":{"minecraft:oak_planks":8,"minecraft:crafting_table":1,"minecraft:spruce_planks":4,"minecraft:stick":8,"minecraft:wooden_pickaxe":1,"minecraft:furnace":4},"minecraft:dropped":{"minecraft:bread":2,"minecraft:allium":1,"minecraft:rotten_flesh":2,"vampirism:coffin_white":1,"minecraft:stick":2}},"DataVersion":3465}