{
  "takesapillage:root": {
    "criteria": {
      "always": "2025-05-04 20:56:21 +0000"
    },
    "done": true
  },
  "minecraft:recipes/decorations/crafting_table": {
    "criteria": {
      "unlock_right_away": "2025-05-04 20:56:21 +0000"
    },
    "done": true
  },
  "mowziesmobs:root": {
    "criteria": {
      "custom_test_name": "2025-05-04 20:56:21 +0000"
    },
    "done": true
  },
  "cataclysm:root": {
    "criteria": {
      "custom_test_name": "2025-05-04 20:56:21 +0000"
    },
    "done": true
  },
  "incendium:technical/new_player": {
    "criteria": {
      "requirement": "2025-05-04 20:56:21 +0000"
    },
    "done": true
  },
  "incendium:technical/scroll_of_returning": {
    "criteria": {
      "log_spam_fixer": "2025-05-04 20:56:22 +0000"
    },
    "done": false
  },
  "incendium:technical/using/ragnarok": {
    "criteria": {
      "log_spam_fixer": "2025-05-04 20:56:22 +0000"
    },
    "done": false
  },
  "incendium:technical/using/trailblazer": {
    "criteria": {
      "log_spam_fixer": "2025-05-04 20:56:22 +0000"
    },
    "done": false
  },
  "minecraft:adventure/adventuring_time": {
    "criteria": {
      "minecraft:taiga": "2025-05-04 22:57:50 +0000",
      "minecraft:birch_forest": "2025-05-06 03:19:12 +0000",
      "minecraft:beach": "2025-05-06 03:13:20 +0000",
      "minecraft:mangrove_swamp": "2025-05-06 03:26:22 +0000",
      "minecraft:sparse_jungle": "2025-05-06 03:25:50 +0000",
      "minecraft:river": "2025-05-05 15:52:41 +0000",
      "minecraft:lukewarm_ocean": "2025-05-06 14:35:36 +0000",
      "minecraft:snowy_plains": "2025-05-06 02:50:31 +0000",
      "minecraft:snowy_taiga": "2025-05-04 20:56:22 +0000",
      "minecraft:forest": "2025-05-04 22:59:01 +0000",
      "minecraft:lush_caves": "2025-05-04 22:58:01 +0000",
      "minecraft:frozen_ocean": "2025-05-04 22:58:11 +0000",
      "minecraft:old_growth_birch_forest": "2025-05-06 03:19:03 +0000",
      "minecraft:savanna": "2025-05-06 03:26:57 +0000",
      "minecraft:plains": "2025-05-05 15:33:27 +0000"
    },
    "done": false
  },
  "incendium:technical/using/shield": {
    "criteria": {
      "log_spam_fixer": "2025-05-04 20:56:22 +0000"
    },
    "done": false
  },
  "travelersbackpack:recipes/misc/fox": {
    "criteria": {
      "has_sweet_berries": "2025-05-04 23:01:44 +0000"
    },
    "done": true
  },
  "minecraft:husbandry/root": {
    "criteria": {
      "consumed_item": "2025-05-04 23:01:54 +0000"
    },
    "done": true
  },
  "minecraft:husbandry/balanced_diet": {
    "criteria": {
      "sweet_berries": "2025-05-04 23:01:54 +0000",
      "pumpkin_pie": "2025-05-04 23:02:40 +0000",
      "bread": "2025-05-04 23:05:05 +0000"
    },
    "done": false
  },
  "minecraft:adventure/sleep_in_bed": {
    "criteria": {
      "slept_in_bed": "2025-05-04 23:02:19 +0000"
    },
    "done": true
  },
  "minecraft:recipes/building_blocks/spruce_wood": {
    "criteria": {
      "has_log": "2025-05-04 23:02:35 +0000"
    },
    "done": true
  },
  "vampirism:recipes/decorations/general/fire_place": {
    "criteria": {
      "has_logs": "2025-05-04 23:02:35 +0000"
    },
    "done": true
  },
  "minecraft:recipes/building_blocks/spruce_planks": {
    "criteria": {
      "has_logs": "2025-05-04 23:02:35 +0000"
    },
    "done": true
  },
  "vampirism:recipes/food/general/garlic_bread": {
    "criteria": {
      "has_bread": "2025-05-04 23:02:35 +0000"
    },
    "done": true
  },
  "minecraft:recipes/misc/charcoal": {
    "criteria": {
      "has_log": "2025-05-04 23:02:35 +0000"
    },
    "done": true
  },
  "minecraft:recipes/combat/iron_leggings": {
    "criteria": {
      "has_iron_ingot": "2025-05-04 23:03:01 +0000"
    },
    "done": true
  },
  "vampirism:recipes/decorations/general/grave_cage": {
    "criteria": {
      "has_iron": "2025-05-04 23:03:01 +0000"
    },
    "done": true
  },
  "minecraft:recipes/combat/iron_chestplate": {
    "criteria": {
      "has_iron_ingot": "2025-05-04 23:03:01 +0000"
    },
    "done": true
  },
  "vampirism:recipes/decorations/hunter/item_med_chair": {
    "criteria": {
      "has_iron_ingot": "2025-05-04 23:03:01 +0000"
    },
    "done": true
  },
  "travelersbackpack:recipes/misc/backpack_tank": {
    "criteria": {
      "has_iron": "2025-05-04 23:03:01 +0000"
    },
    "done": true
  },
  "werewolves:recipes/misc/weapontable/crossbow_arrow_silver_bolt": {
    "criteria": {
      "has_iron": "2025-05-04 23:03:01 +0000"
    },
    "done": true
  },
  "minecraft:recipes/misc/iron_nugget": {
    "criteria": {
      "has_iron_ingot": "2025-05-04 23:03:01 +0000"
    },
    "done": true
  },
  "minecraft:recipes/misc/bucket": {
    "criteria": {
      "has_iron_ingot": "2025-05-04 23:03:01 +0000"
    },
    "done": true
  },
  "minecraft:recipes/combat/iron_helmet": {
    "criteria": {
      "has_iron_ingot": "2025-05-04 23:03:01 +0000"
    },
    "done": true
  },
  "minecraft:recipes/transportation/minecart": {
    "criteria": {
      "has_iron_ingot": "2025-05-04 23:03:01 +0000"
    },
    "done": true
  },
  "minecraft:recipes/tools/iron_hoe": {
    "criteria": {
      "has_iron_ingot": "2025-05-04 23:03:01 +0000"
    },
    "done": true
  },
  "minecraft:story/smelt_iron": {
    "criteria": {
      "iron": "2025-05-04 23:03:01 +0000"
    },
    "done": true
  },
  "minecraft:recipes/tools/shears": {
    "criteria": {
      "has_iron_ingot": "2025-05-04 23:03:01 +0000"
    },
    "done": true
  },
  "vampirism:recipes/combat/weapontable/crucifix_enhanced": {
    "criteria": {
      "iron": "2025-05-04 23:03:01 +0000"
    },
    "done": true
  },
  "vampirism:recipes/misc/vampire/blood_infused_enhanced_iron_ingot": {
    "criteria": {
      "has_iron": "2025-05-04 23:03:01 +0000"
    },
    "done": true
  },
  "minecraft:recipes/decorations/chain": {
    "criteria": {
      "has_iron_ingot": "2025-05-04 23:03:01 +0000"
    },
    "done": true
  },
  "vampirism:recipes/misc/vampire/blood_infused_iron_ingot": {
    "criteria": {
      "has_iron": "2025-05-04 23:03:01 +0000"
    },
    "done": true
  },
  "minecraft:recipes/building_blocks/iron_block": {
    "criteria": {
      "has_iron_ingot": "2025-05-04 23:03:01 +0000"
    },
    "done": true
  },
  "minecraft:recipes/decorations/smithing_table": {
    "criteria": {
      "has_iron_ingot": "2025-05-04 23:03:01 +0000"
    },
    "done": true
  },
  "vampirism:recipes/decorations/vampire/candelabra": {
    "criteria": {
      "has_iron": "2025-05-04 23:03:01 +0000"
    },
    "done": true
  },
  "vampirism:recipes/decorations/vampire/altar_tip": {
    "criteria": {
      "has_iron": "2025-05-04 23:03:01 +0000"
    },
    "done": true
  },
  "minecraft:recipes/combat/iron_sword": {
    "criteria": {
      "has_iron_ingot": "2025-05-04 23:03:01 +0000"
    },
    "done": true
  },
  "minecraft:recipes/tools/iron_pickaxe": {
    "criteria": {
      "has_iron_ingot": "2025-05-04 23:03:01 +0000"
    },
    "done": true
  },
  "minecraft:recipes/combat/shield": {
    "criteria": {
      "has_iron_ingot": "2025-05-04 23:03:01 +0000"
    },
    "done": true
  },
  "vampirism:recipes/decorations/vampire/blood_container": {
    "criteria": {
      "has_iron": "2025-05-04 23:03:01 +0000"
    },
    "done": true
  },
  "minecraft:recipes/redstone/hopper": {
    "criteria": {
      "has_iron_ingot": "2025-05-04 23:03:01 +0000"
    },
    "done": true
  },
  "travelersbackpack:recipes/misc/iron": {
    "criteria": {
      "has_iron_ingot": "2025-05-04 23:03:01 +0000"
    },
    "done": true
  },
  "minecraft:recipes/decorations/iron_bars": {
    "criteria": {
      "has_iron_ingot": "2025-05-04 23:03:01 +0000"
    },
    "done": true
  },
  "travelersbackpack:recipes/misc/iron_tier_upgrade": {
    "criteria": {
      "has_iron_ingot": "2025-05-04 23:03:01 +0000"
    },
    "done": true
  },
  "minecraft:recipes/combat/iron_boots": {
    "criteria": {
      "has_iron_ingot": "2025-05-04 23:03:01 +0000"
    },
    "done": true
  },
  "travelersbackpack:recipes/misc/hose_nozzle": {
    "criteria": {
      "has_iron": "2025-05-04 23:03:01 +0000"
    },
    "done": true
  },
  "vampirism:recipes/decorations/vampire/candle_stick": {
    "criteria": {
      "has_iron": "2025-05-04 23:03:01 +0000"
    },
    "done": true
  },
  "minecraft:recipes/decorations/lantern": {
    "criteria": {
      "has_iron_ingot": "2025-05-04 23:03:01 +0000"
    },
    "done": true
  },
  "minecraft:recipes/tools/iron_shovel": {
    "criteria": {
      "has_iron_ingot": "2025-05-04 23:03:01 +0000"
    },
    "done": true
  },
  "vampirism:recipes/decorations/hunter/alchemical_cauldron": {
    "criteria": {
      "has_iron": "2025-05-04 23:03:01 +0000"
    },
    "done": true
  },
  "vampirism:recipes/combat/hunter/crossbow_arrow_normal": {
    "criteria": {
      "has_iron_ingot": "2025-05-04 23:03:01 +0000"
    },
    "done": true
  },
  "vampirism:recipes/decorations/vampire/candelabra_candles": {
    "criteria": {
      "has_iron": "2025-05-04 23:03:01 +0000"
    },
    "done": true
  },
  "minecraft:recipes/redstone/iron_trapdoor": {
    "criteria": {
      "has_iron_ingot": "2025-05-04 23:03:01 +0000"
    },
    "done": true
  },
  "vampirism:recipes/decorations/hunter/weapon_table": {
    "criteria": {
      "has_iron_ingot": "2025-05-04 23:03:01 +0000"
    },
    "done": true
  },
  "minecraft:recipes/tools/iron_axe": {
    "criteria": {
      "has_iron_ingot": "2025-05-04 23:03:01 +0000"
    },
    "done": true
  },
  "minecraft:recipes/combat/crossbow": {
    "criteria": {
      "has_iron_ingot": "2025-05-04 23:03:01 +0000"
    },
    "done": true
  },
  "minecraft:recipes/redstone/iron_door": {
    "criteria": {
      "has_iron_ingot": "2025-05-04 23:03:01 +0000"
    },
    "done": true
  },
  "minecraft:recipes/redstone/heavy_weighted_pressure_plate": {
    "criteria": {
      "has_iron_ingot": "2025-05-04 23:03:01 +0000"
    },
    "done": true
  },
  "vampirism:main/root": {
    "criteria": {
      "second": "2025-05-04 23:03:02 +0000"
    },
    "done": true
  },
  "vampirism:recipes/decorations/hunter/cross": {
    "criteria": {
      "has_holy": "2025-05-04 23:03:02 +0000"
    },
    "done": true
  },
  "vampirism:recipes/misc/vampire/garlic_finder": {
    "criteria": {
      "has_garlic": "2025-05-04 23:03:02 +0000"
    },
    "done": true
  },
  "vampirism:recipes/combat/hunter/crucifix": {
    "criteria": {
      "holy_water": "2025-05-04 23:03:02 +0000"
    },
    "done": true
  },
  "minecraft:recipes/decorations/glow_item_frame": {
    "criteria": {
      "has_item_frame": "2025-05-04 23:03:15 +0000"
    },
    "done": true
  },
  "minecraft:recipes/decorations/chest": {
    "criteria": {
      "has_lots_of_items": "2025-05-04 23:03:15 +0000"
    },
    "done": true
  },
  "vampirism:recipes/decorations/hunter/hunter_table": {
    "criteria": {
      "has_fang": "2025-05-04 23:03:15 +0000"
    },
    "done": true
  },
  "vampirism:recipes/decorations/general/vampire_rack": {
    "criteria": {
      "has_fangs": "2025-05-04 23:03:15 +0000"
    },
    "done": true
  },
  "minecraft:recipes/food/baked_potato_from_campfire_cooking": {
    "criteria": {
      "has_potato": "2025-05-04 23:03:25 +0000"
    },
    "done": true
  },
  "minecraft:recipes/food/baked_potato": {
    "criteria": {
      "has_potato": "2025-05-04 23:03:25 +0000"
    },
    "done": true
  },
  "minecraft:recipes/food/baked_potato_from_smoking": {
    "criteria": {
      "has_potato": "2025-05-04 23:03:25 +0000"
    },
    "done": true
  },
  "minecraft:story/obtain_armor": {
    "criteria": {
      "iron_chestplate": "2025-05-04 23:04:01 +0000"
    },
    "done": true
  },
  "minecraft:recipes/misc/iron_nugget_from_smelting": {
    "criteria": {
      "has_iron_chestplate": "2025-05-04 23:04:01 +0000"
    },
    "done": true
  },
  "minecraft:recipes/misc/iron_nugget_from_blasting": {
    "criteria": {
      "has_iron_chestplate": "2025-05-04 23:04:01 +0000"
    },
    "done": true
  },
  "minecraft:recipes/building_blocks/clay": {
    "criteria": {
      "has_clay_ball": "2025-05-04 23:04:10 +0000"
    },
    "done": true
  },
  "minecraft:recipes/misc/brick": {
    "criteria": {
      "has_clay_ball": "2025-05-04 23:04:10 +0000"
    },
    "done": true
  },
  "minecraft:recipes/misc/magenta_dye_from_allium": {
    "criteria": {
      "has_allium": "2025-05-04 23:04:21 +0000"
    },
    "done": true
  },
  "minecraft:recipes/building_blocks/oak_planks": {
    "criteria": {
      "has_logs": "2025-05-04 23:04:35 +0000"
    },
    "done": true
  },
  "minecraft:recipes/building_blocks/oak_wood": {
    "criteria": {
      "has_log": "2025-05-04 23:04:35 +0000"
    },
    "done": true
  },
  "minecraft:recipes/transportation/cherry_boat": {
    "criteria": {
      "in_water": "2025-05-04 23:04:37 +0000"
    },
    "done": true
  },
  "minecraft:recipes/transportation/bamboo_raft": {
    "criteria": {
      "in_water": "2025-05-04 23:04:37 +0000"
    },
    "done": true
  },
  "minecraft:recipes/transportation/spruce_boat": {
    "criteria": {
      "in_water": "2025-05-04 23:04:37 +0000"
    },
    "done": true
  },
  "minecraft:recipes/transportation/birch_boat": {
    "criteria": {
      "in_water": "2025-05-04 23:04:37 +0000"
    },
    "done": true
  },
  "minecraft:recipes/transportation/oak_boat": {
    "criteria": {
      "in_water": "2025-05-04 23:04:37 +0000"
    },
    "done": true
  },
  "vampirism:recipes/transportation/cursed_spruce_boat": {
    "criteria": {
      "in_water": "2025-05-04 23:04:37 +0000"
    },
    "done": true
  },
  "minecraft:recipes/transportation/mangrove_boat": {
    "criteria": {
      "in_water": "2025-05-04 23:04:37 +0000"
    },
    "done": true
  },
  "vampirism:recipes/transportation/dark_spruce_boat": {
    "criteria": {
      "in_water": "2025-05-04 23:04:37 +0000"
    },
    "done": true
  },
  "werewolves:recipes/transportation/jacaranda_boat": {
    "criteria": {
      "in_water": "2025-05-04 23:04:37 +0000"
    },
    "done": true
  },
  "minecraft:recipes/transportation/acacia_boat": {
    "criteria": {
      "in_water": "2025-05-04 23:04:37 +0000"
    },
    "done": true
  },
  "werewolves:recipes/transportation/magic_boat": {
    "criteria": {
      "in_water": "2025-05-04 23:04:37 +0000"
    },
    "done": true
  },
  "minecraft:recipes/transportation/jungle_boat": {
    "criteria": {
      "in_water": "2025-05-04 23:04:37 +0000"
    },
    "done": true
  },
  "minecraft:recipes/transportation/dark_oak_boat": {
    "criteria": {
      "in_water": "2025-05-04 23:04:37 +0000"
    },
    "done": true
  },
  "minecraft:recipes/misc/stick": {
    "criteria": {
      "has_the_recipe": "2025-05-04 23:04:41 +0000"
    },
    "done": true
  },
  "minecraft:recipes/decorations/ladder": {
    "criteria": {
      "has_stick": "2025-05-04 23:04:42 +0000"
    },
    "done": true
  },
  "vampirism:recipes/combat/hunter/stake": {
    "criteria": {
      "has_sticks": "2025-05-04 23:04:42 +0000"
    },
    "done": true
  },
  "werewolves:recipes/misc/silver_pickaxe": {
    "criteria": {
      "has_sticks": "2025-05-04 23:04:42 +0000"
    },
    "done": true
  },
  "minecraft:recipes/tools/wooden_axe": {
    "criteria": {
      "has_stick": "2025-05-04 23:04:42 +0000"
    },
    "done": true
  },
  "werewolves:recipes/misc/silver_axe": {
    "criteria": {
      "has_sticks": "2025-05-04 23:04:42 +0000"
    },
    "done": true
  },
  "vampirism:recipes/decorations/general/throne": {
    "criteria": {
      "has_stick": "2025-05-04 23:04:42 +0000"
    },
    "done": true
  },
  "werewolves:recipes/misc/silver_shovel": {
    "criteria": {
      "has_sticks": "2025-05-04 23:04:42 +0000"
    },
    "done": true
  },
  "minecraft:recipes/decorations/campfire": {
    "criteria": {
      "has_stick": "2025-05-04 23:04:42 +0000"
    },
    "done": true
  },
  "minecraft:recipes/tools/wooden_hoe": {
    "criteria": {
      "has_stick": "2025-05-04 23:04:42 +0000"
    },
    "done": true
  },
  "minecraft:recipes/tools/wooden_pickaxe": {
    "criteria": {
      "has_stick": "2025-05-04 23:04:42 +0000"
    },
    "done": true
  },
  "minecraft:recipes/tools/wooden_shovel": {
    "criteria": {
      "has_stick": "2025-05-04 23:04:42 +0000"
    },
    "done": true
  },
  "werewolves:recipes/misc/silver_sword": {
    "criteria": {
      "has_sticks": "2025-05-04 23:04:42 +0000"
    },
    "done": true
  },
  "paraglider:recipes/misc/paraglider": {
    "criteria": {
      "has_stick": "2025-05-04 23:04:42 +0000"
    },
    "done": true
  },
  "minecraft:recipes/combat/wooden_sword": {
    "criteria": {
      "has_stick": "2025-05-04 23:04:42 +0000"
    },
    "done": true
  },
  "werewolves:recipes/misc/silver_hoe": {
    "criteria": {
      "has_sticks": "2025-05-04 23:04:42 +0000"
    },
    "done": true
  },
  "werewolves:recipes/misc/stone_altar_fire_bowl": {
    "criteria": {
      "has_planks": "2025-05-04 23:04:54 +0000"
    },
    "done": true
  },
  "minecraft:recipes/decorations/spruce_sign": {
    "criteria": {
      "has_planks": "2025-05-04 23:04:54 +0000"
    },
    "done": true
  },
  "vampirism:recipes/decorations/vampire/altar_inspiration": {
    "criteria": {
      "has_planks": "2025-05-04 23:04:54 +0000"
    },
    "done": true
  },
  "minecraft:recipes/decorations/spruce_fence": {
    "criteria": {
      "has_planks": "2025-05-04 23:04:54 +0000"
    },
    "done": true
  },
  "minecraft:recipes/building_blocks/spruce_slab": {
    "criteria": {
      "has_planks": "2025-05-04 23:04:54 +0000"
    },
    "done": true
  },
  "minecraft:recipes/redstone/spruce_button": {
    "criteria": {
      "has_planks": "2025-05-04 23:04:54 +0000"
    },
    "done": true
  },
  "minecraft:recipes/redstone/spruce_pressure_plate": {
    "criteria": {
      "has_planks": "2025-05-04 23:04:54 +0000"
    },
    "done": true
  },
  "vampirism:recipes/decorations/bat_cage": {
    "criteria": {
      "has_planks": "2025-05-04 23:04:54 +0000"
    },
    "done": true
  },
  "minecraft:recipes/redstone/spruce_trapdoor": {
    "criteria": {
      "has_planks": "2025-05-04 23:04:54 +0000"
    },
    "done": true
  },
  "minecraft:recipes/redstone/spruce_door": {
    "criteria": {
      "has_planks": "2025-05-04 23:04:54 +0000"
    },
    "done": true
  },
  "minecraft:recipes/redstone/spruce_fence_gate": {
    "criteria": {
      "has_planks": "2025-05-04 23:04:54 +0000"
    },
    "done": true
  },
  "vampirism:recipes/combat/alchemy_table": {
    "criteria": {
      "has_planks": "2025-05-04 23:04:54 +0000"
    },
    "done": true
  },
  "minecraft:recipes/decorations/barrel": {
    "criteria": {
      "has_planks": "2025-05-04 23:04:54 +0000"
    },
    "done": true
  },
  "minecraft:recipes/building_blocks/spruce_stairs": {
    "criteria": {
      "has_planks": "2025-05-04 23:04:54 +0000"
    },
    "done": true
  },
  "vampirism:recipes/decorations/general/altar_cleansing": {
    "criteria": {
      "has_vampire_book": "2025-05-04 23:04:54 +0000"
    },
    "done": true
  },
  "minecraft:recipes/building_blocks/coarse_dirt": {
    "criteria": {
      "has_gravel": "2025-05-04 23:05:30 +0000"
    },
    "done": true
  },
  "minecraft:recipes/building_blocks/light_gray_concrete_powder": {
    "criteria": {
      "has_gravel": "2025-05-04 23:05:30 +0000"
    },
    "done": true
  },
  "minecraft:recipes/building_blocks/pink_concrete_powder": {
    "criteria": {
      "has_gravel": "2025-05-04 23:05:30 +0000"
    },
    "done": true
  },
  "minecraft:recipes/building_blocks/red_concrete_powder": {
    "criteria": {
      "has_gravel": "2025-05-04 23:05:30 +0000"
    },
    "done": true
  },
  "minecraft:recipes/building_blocks/brown_concrete_powder": {
    "criteria": {
      "has_gravel": "2025-05-04 23:05:30 +0000"
    },
    "done": true
  },
  "minecraft:recipes/building_blocks/light_blue_concrete_powder": {
    "criteria": {
      "has_gravel": "2025-05-04 23:05:30 +0000"
    },
    "done": true
  },
  "minecraft:recipes/building_blocks/green_concrete_powder": {
    "criteria": {
      "has_gravel": "2025-05-04 23:05:30 +0000"
    },
    "done": true
  },
  "minecraft:recipes/building_blocks/blue_concrete_powder": {
    "criteria": {
      "has_gravel": "2025-05-04 23:05:30 +0000"
    },
    "done": true
  },
  "minecraft:recipes/building_blocks/white_concrete_powder": {
    "criteria": {
      "has_gravel": "2025-05-04 23:05:30 +0000"
    },
    "done": true
  },
  "minecraft:recipes/building_blocks/lime_concrete_powder": {
    "criteria": {
      "has_gravel": "2025-05-04 23:05:30 +0000"
    },
    "done": true
  },
  "minecraft:recipes/building_blocks/orange_concrete_powder": {
    "criteria": {
      "has_gravel": "2025-05-04 23:05:30 +0000"
    },
    "done": true
  },
  "minecraft:recipes/building_blocks/magenta_concrete_powder": {
    "criteria": {
      "has_gravel": "2025-05-04 23:05:30 +0000"
    },
    "done": true
  },
  "minecraft:recipes/building_blocks/yellow_concrete_powder": {
    "criteria": {
      "has_gravel": "2025-05-04 23:05:30 +0000"
    },
    "done": true
  },
  "minecraft:recipes/building_blocks/gray_concrete_powder": {
    "criteria": {
      "has_gravel": "2025-05-04 23:05:30 +0000"
    },
    "done": true
  },
  "minecraft:recipes/building_blocks/black_concrete_powder": {
    "criteria": {
      "has_gravel": "2025-05-04 23:05:30 +0000"
    },
    "done": true
  },
  "minecraft:recipes/building_blocks/purple_concrete_powder": {
    "criteria": {
      "has_gravel": "2025-05-04 23:05:30 +0000"
    },
    "done": true
  },
  "minecraft:recipes/building_blocks/cyan_concrete_powder": {
    "criteria": {
      "has_gravel": "2025-05-04 23:05:30 +0000"
    },
    "done": true
  },
  "minecraft:recipes/redstone/lever": {
    "criteria": {
      "has_cobblestone": "2025-05-04 23:05:34 +0000"
    },
    "done": true
  },
  "minecraft:recipes/combat/stone_sword": {
    "criteria": {
      "has_cobblestone": "2025-05-04 23:05:34 +0000"
    },
    "done": true
  },
  "minecraft:recipes/decorations/cobblestone_wall": {
    "criteria": {
      "has_cobblestone": "2025-05-04 23:05:34 +0000"
    },
    "done": true
  },
  "minecraft:recipes/tools/stone_axe": {
    "criteria": {
      "has_cobblestone": "2025-05-04 23:05:34 +0000"
    },
    "done": true
  },
  "minecraft:story/mine_stone": {
    "criteria": {
      "get_stone": "2025-05-04 23:05:34 +0000"
    },
    "done": true
  },
  "minecraft:recipes/decorations/furnace": {
    "criteria": {
      "has_cobblestone": "2025-05-04 23:05:34 +0000"
    },
    "done": true
  },
  "minecraft:recipes/building_blocks/cobblestone_slab_from_cobblestone_stonecutting": {
    "criteria": {
      "has_cobblestone": "2025-05-04 23:05:34 +0000"
    },
    "done": true
  },
  "minecraft:recipes/building_blocks/stone": {
    "criteria": {
      "has_cobblestone": "2025-05-04 23:05:34 +0000"
    },
    "done": true
  },
  "vampirism:recipes/decorations/general/tombstone2": {
    "criteria": {
      "has_coble": "2025-05-04 23:05:34 +0000"
    },
    "done": true
  },
  "minecraft:recipes/tools/stone_pickaxe": {
    "criteria": {
      "has_cobblestone": "2025-05-04 23:05:34 +0000"
    },
    "done": true
  },
  "minecraft:recipes/building_blocks/cobblestone_slab": {
    "criteria": {
      "has_cobblestone": "2025-05-04 23:05:34 +0000"
    },
    "done": true
  },
  "minecraft:recipes/decorations/cobblestone_wall_from_cobblestone_stonecutting": {
    "criteria": {
      "has_cobblestone": "2025-05-04 23:05:34 +0000"
    },
    "done": true
  },
  "minecraft:recipes/building_blocks/cobblestone_stairs_from_cobblestone_stonecutting": {
    "criteria": {
      "has_cobblestone": "2025-05-04 23:05:34 +0000"
    },
    "done": true
  },
  "minecraft:recipes/building_blocks/cobblestone_stairs": {
    "criteria": {
      "has_cobblestone": "2025-05-04 23:05:34 +0000"
    },
    "done": true
  },
  "minecraft:recipes/tools/stone_hoe": {
    "criteria": {
      "has_cobblestone": "2025-05-04 23:05:34 +0000"
    },
    "done": true
  },
  "minecraft:recipes/tools/stone_shovel": {
    "criteria": {
      "has_cobblestone": "2025-05-04 23:05:34 +0000"
    },
    "done": true
  },
  "minecraft:adventure/root": {
    "criteria": {
      "killed_by_something": "2025-05-05 14:34:47 +0000"
    },
    "done": true
  },
  "minecraft:story/iron_tools": {
    "criteria": {
      "iron_pickaxe": "2025-05-05 14:46:04 +0000"
    },
    "done": true
  },
  "minecraft:adventure/kill_all_mobs": {
    "criteria": {
      "minecraft:skeleton": "2025-05-05 15:46:58 +0000",
      "minecraft:zombie": "2025-05-05 14:48:46 +0000"
    },
    "done": false
  },
  "minecraft:adventure/kill_a_mob": {
    "criteria": {
      "minecraft:zombie": "2025-05-05 14:48:46 +0000"
    },
    "done": true
  },
  "vampirism:recipes/decorations/vampire/coffin_gray_from_white": {
    "criteria": {
      "has_coffin": "2025-05-05 14:49:19 +0000"
    },
    "done": true
  },
  "vampirism:recipes/decorations/vampire/coffin_brown_from_white": {
    "criteria": {
      "has_coffin": "2025-05-05 14:49:19 +0000"
    },
    "done": true
  },
  "vampirism:recipes/decorations/vampire/coffin_green_from_white": {
    "criteria": {
      "has_coffin": "2025-05-05 14:49:19 +0000"
    },
    "done": true
  },
  "vampirism:recipes/decorations/vampire/coffin_cyan_from_white": {
    "criteria": {
      "has_coffin": "2025-05-05 14:49:19 +0000"
    },
    "done": true
  },
  "vampirism:recipes/decorations/vampire/coffin_orange_from_white": {
    "criteria": {
      "has_coffin": "2025-05-05 14:49:19 +0000"
    },
    "done": true
  },
  "vampirism:recipes/decorations/vampire/coffin_blue_from_white": {
    "criteria": {
      "has_coffin": "2025-05-05 14:49:19 +0000"
    },
    "done": true
  },
  "vampirism:recipes/decorations/vampire/coffin_yellow_from_white": {
    "criteria": {
      "has_coffin": "2025-05-05 14:49:19 +0000"
    },
    "done": true
  },
  "vampirism:recipes/decorations/vampire/coffin_purple_from_white": {
    "criteria": {
      "has_coffin": "2025-05-05 14:49:19 +0000"
    },
    "done": true
  },
  "vampirism:recipes/decorations/vampire/coffin_light_blue_from_white": {
    "criteria": {
      "has_coffin": "2025-05-05 14:49:19 +0000"
    },
    "done": true
  },
  "vampirism:recipes/decorations/vampire/coffin_lime_from_white": {
    "criteria": {
      "has_coffin": "2025-05-05 14:49:19 +0000"
    },
    "done": true
  },
  "vampirism:recipes/decorations/vampire/coffin_black_from_white": {
    "criteria": {
      "has_coffin": "2025-05-05 14:49:19 +0000"
    },
    "done": true
  },
  "vampirism:recipes/decorations/vampire/coffin_red_from_white": {
    "criteria": {
      "has_coffin": "2025-05-05 14:49:19 +0000"
    },
    "done": true
  },
  "vampirism:recipes/decorations/vampire/coffin_pink_from_white": {
    "criteria": {
      "has_coffin": "2025-05-05 14:49:19 +0000"
    },
    "done": true
  },
  "vampirism:recipes/decorations/vampire/coffin_magenta_from_white": {
    "criteria": {
      "has_coffin": "2025-05-05 14:49:19 +0000"
    },
    "done": true
  },
  "vampirism:recipes/decorations/vampire/coffin_light_gray_from_white": {
    "criteria": {
      "has_coffin": "2025-05-05 14:49:19 +0000"
    },
    "done": true
  },
  "minecraft:recipes/misc/paper": {
    "criteria": {
      "has_reeds": "2025-05-05 14:57:07 +0000"
    },
    "done": true
  },
  "minecraft:recipes/misc/sugar_from_sugar_cane": {
    "criteria": {
      "has_sugar_cane": "2025-05-05 14:57:07 +0000"
    },
    "done": true
  },
  "minecraft:recipes/building_blocks/glass": {
    "criteria": {
      "has_smelts_to_glass": "2025-05-05 15:04:46 +0000"
    },
    "done": true
  },
  "minecraft:recipes/building_blocks/sandstone": {
    "criteria": {
      "has_sand": "2025-05-05 15:04:46 +0000"
    },
    "done": true
  },
  "minecraft:recipes/misc/purple_dye": {
    "criteria": {
      "has_wolfsbane": "2025-05-05 15:05:06 +0000"
    },
    "done": true
  },
  "paraglider:root": {
    "criteria": {
      "crafting_table": "2025-05-05 15:05:47 +0000"
    },
    "done": true
  },
  "minecraft:story/root": {
    "criteria": {
      "crafting_table": "2025-05-05 15:05:47 +0000"
    },
    "done": true
  },
  "minecraft:recipes/decorations/smoker": {
    "criteria": {
      "has_furnace": "2025-05-05 15:05:57 +0000"
    },
    "done": true
  },
  "vampirism:recipes/alchemy_table/alchemy_table/plant_oil": {
    "criteria": {
      "has_wheat_seeds": "2025-05-05 15:07:31 +0000"
    },
    "done": true
  },
  "minecraft:recipes/building_blocks/stone_bricks": {
    "criteria": {
      "has_stone": "2025-05-05 15:08:22 +0000"
    },
    "done": true
  },
  "minecraft:recipes/building_blocks/stone_bricks_from_stone_stonecutting": {
    "criteria": {
      "has_stone": "2025-05-05 15:08:22 +0000"
    },
    "done": true
  },
  "minecraft:recipes/building_blocks/stone_slab": {
    "criteria": {
      "has_stone": "2025-05-05 15:08:22 +0000"
    },
    "done": true
  },
  "minecraft:recipes/building_blocks/stone_stairs_from_stone_stonecutting": {
    "criteria": {
      "has_stone": "2025-05-05 15:08:22 +0000"
    },
    "done": true
  },
  "minecraft:recipes/redstone/stone_button": {
    "criteria": {
      "has_stone": "2025-05-05 15:08:22 +0000"
    },
    "done": true
  },
  "minecraft:recipes/decorations/stonecutter": {
    "criteria": {
      "has_stone": "2025-05-05 15:08:22 +0000"
    },
    "done": true
  },
  "minecraft:recipes/redstone/stone_pressure_plate": {
    "criteria": {
      "has_stone": "2025-05-05 15:08:22 +0000"
    },
    "done": true
  },
  "minecraft:recipes/building_blocks/smooth_stone": {
    "criteria": {
      "has_stone": "2025-05-05 15:08:22 +0000"
    },
    "done": true
  },
  "minecraft:recipes/decorations/stone_brick_walls_from_stone_stonecutting": {
    "criteria": {
      "has_stone": "2025-05-05 15:08:22 +0000"
    },
    "done": true
  },
  "minecraft:recipes/building_blocks/stone_brick_slab_from_stone_stonecutting": {
    "criteria": {
      "has_stone": "2025-05-05 15:08:22 +0000"
    },
    "done": true
  },
  "minecraft:recipes/building_blocks/stone_brick_stairs_from_stone_stonecutting": {
    "criteria": {
      "has_stone": "2025-05-05 15:08:22 +0000"
    },
    "done": true
  },
  "minecraft:recipes/building_blocks/stone_slab_from_stone_stonecutting": {
    "criteria": {
      "has_stone": "2025-05-05 15:08:22 +0000"
    },
    "done": true
  },
  "minecraft:recipes/building_blocks/chiseled_stone_bricks_stone_from_stonecutting": {
    "criteria": {
      "has_stone": "2025-05-05 15:08:22 +0000"
    },
    "done": true
  },
  "minecraft:recipes/building_blocks/stone_stairs": {
    "criteria": {
      "has_stone": "2025-05-05 15:08:22 +0000"
    },
    "done": true
  },
  "travelersbackpack:recipes/misc/coal": {
    "criteria": {
      "has_coal": "2025-05-05 15:09:57 +0000"
    },
    "done": true
  },
  "minecraft:recipes/building_blocks/light_blue_stained_glass": {
    "criteria": {
      "has_glass": "2025-05-05 15:22:06 +0000"
    },
    "done": true
  },
  "minecraft:recipes/building_blocks/green_stained_glass": {
    "criteria": {
      "has_glass": "2025-05-05 15:22:06 +0000"
    },
    "done": true
  },
  "minecraft:recipes/building_blocks/brown_stained_glass": {
    "criteria": {
      "has_glass": "2025-05-05 15:22:06 +0000"
    },
    "done": true
  },
  "minecraft:recipes/building_blocks/blue_stained_glass": {
    "criteria": {
      "has_glass": "2025-05-05 15:22:06 +0000"
    },
    "done": true
  },
  "vampirism:recipes/misc/vampire_beacon": {
    "criteria": {
      "has_glass": "2025-05-05 15:22:06 +0000"
    },
    "done": true
  },
  "minecraft:recipes/building_blocks/orange_stained_glass": {
    "criteria": {
      "has_glass": "2025-05-05 15:22:06 +0000"
    },
    "done": true
  },
  "minecraft:recipes/building_blocks/pink_stained_glass": {
    "criteria": {
      "has_glass": "2025-05-05 15:22:06 +0000"
    },
    "done": true
  },
  "minecraft:recipes/building_blocks/black_stained_glass": {
    "criteria": {
      "has_glass": "2025-05-05 15:22:06 +0000"
    },
    "done": true
  },
  "minecraft:recipes/building_blocks/gray_stained_glass": {
    "criteria": {
      "has_glass": "2025-05-05 15:22:06 +0000"
    },
    "done": true
  },
  "minecraft:recipes/building_blocks/lime_stained_glass": {
    "criteria": {
      "has_glass": "2025-05-05 15:22:06 +0000"
    },
    "done": true
  },
  "minecraft:recipes/decorations/glass_pane": {
    "criteria": {
      "has_glass": "2025-05-05 15:22:06 +0000"
    },
    "done": true
  },
  "minecraft:recipes/building_blocks/magenta_stained_glass": {
    "criteria": {
      "has_glass": "2025-05-05 15:22:06 +0000"
    },
    "done": true
  },
  "minecraft:recipes/building_blocks/white_stained_glass": {
    "criteria": {
      "has_glass": "2025-05-05 15:22:06 +0000"
    },
    "done": true
  },
  "minecraft:recipes/building_blocks/red_stained_glass": {
    "criteria": {
      "has_glass": "2025-05-05 15:22:06 +0000"
    },
    "done": true
  },
  "vampirism:recipes/misc/general/injection_0": {
    "criteria": {
      "has_glass": "2025-05-05 15:22:06 +0000"
    },
    "done": true
  },
  "minecraft:recipes/brewing/glass_bottle": {
    "criteria": {
      "has_glass": "2025-05-05 15:22:06 +0000"
    },
    "done": true
  },
  "minecraft:recipes/building_blocks/light_gray_stained_glass": {
    "criteria": {
      "has_glass": "2025-05-05 15:22:06 +0000"
    },
    "done": true
  },
  "minecraft:recipes/building_blocks/cyan_stained_glass": {
    "criteria": {
      "has_glass": "2025-05-05 15:22:06 +0000"
    },
    "done": true
  },
  "minecraft:recipes/building_blocks/purple_stained_glass": {
    "criteria": {
      "has_glass": "2025-05-05 15:22:06 +0000"
    },
    "done": true
  },
  "minecraft:recipes/building_blocks/yellow_stained_glass": {
    "criteria": {
      "has_glass": "2025-05-05 15:22:06 +0000"
    },
    "done": true
  },
  "minecraft:recipes/building_blocks/coal_block": {
    "criteria": {
      "has_coal": "2025-05-05 15:22:38 +0000"
    },
    "done": true
  },
  "minecraft:recipes/misc/raw_silver_block": {
    "criteria": {
      "has_raw_silver": "2025-05-05 15:27:47 +0000"
    },
    "done": true
  },
  "minecraft:recipes/misc/silver_ingot_from_blasting_raw_silver": {
    "criteria": {
      "has_raw_silver": "2025-05-05 15:27:47 +0000"
    },
    "done": true
  },
  "minecraft:recipes/misc/silver_ingot_from_smelting_raw_silver": {
    "criteria": {
      "has_raw_silver": "2025-05-05 15:27:47 +0000"
    },
    "done": true
  },
  "minecraft:recipes/decorations/torch": {
    "criteria": {
      "has_the_recipe": "2025-05-05 15:28:30 +0000"
    },
    "done": true
  },
  "minecraft:recipes/tools/spyglass": {
    "criteria": {
      "has_amethyst_shard": "2025-05-05 15:28:48 +0000"
    },
    "done": true
  },
  "minecraft:recipes/redstone/calibrated_sculk_sensor": {
    "criteria": {
      "has_amethyst_shard": "2025-05-05 15:28:48 +0000"
    },
    "done": true
  },
  "minecraft:recipes/building_blocks/tinted_glass": {
    "criteria": {
      "has_amethyst_shard": "2025-05-05 15:28:48 +0000"
    },
    "done": true
  },
  "minecraft:recipes/building_blocks/amethyst_block": {
    "criteria": {
      "has_amethyst_shard": "2025-05-05 15:28:48 +0000"
    },
    "done": true
  },
  "minecraft:recipes/building_blocks/raw_iron_block": {
    "criteria": {
      "has_raw_iron": "2025-05-05 15:32:42 +0000"
    },
    "done": true
  },
  "minecraft:recipes/misc/iron_ingot_from_smelting_raw_iron": {
    "criteria": {
      "has_raw_iron": "2025-05-05 15:32:42 +0000"
    },
    "done": true
  },
  "minecraft:recipes/misc/iron_ingot_from_blasting_raw_iron": {
    "criteria": {
      "has_raw_iron": "2025-05-05 15:32:42 +0000"
    },
    "done": true
  },
  "minecraft:recipes/building_blocks/granite_slab_from_granite_stonecutting": {
    "criteria": {
      "has_granite": "2025-05-05 15:39:16 +0000"
    },
    "done": true
  },
  "minecraft:recipes/decorations/granite_wall_from_granite_stonecutting": {
    "criteria": {
      "has_granite": "2025-05-05 15:39:16 +0000"
    },
    "done": true
  },
  "minecraft:recipes/building_blocks/polished_granite_from_granite_stonecutting": {
    "criteria": {
      "has_granite": "2025-05-05 15:39:16 +0000"
    },
    "done": true
  },
  "minecraft:recipes/building_blocks/granite_slab": {
    "criteria": {
      "has_granite": "2025-05-05 15:39:16 +0000"
    },
    "done": true
  },
  "minecraft:recipes/building_blocks/granite_stairs": {
    "criteria": {
      "has_granite": "2025-05-05 15:39:16 +0000"
    },
    "done": true
  },
  "minecraft:recipes/building_blocks/granite_stairs_from_granite_stonecutting": {
    "criteria": {
      "has_granite": "2025-05-05 15:39:16 +0000"
    },
    "done": true
  },
  "minecraft:recipes/decorations/granite_wall": {
    "criteria": {
      "has_granite": "2025-05-05 15:39:16 +0000"
    },
    "done": true
  },
  "minecraft:recipes/building_blocks/polished_granite_slab_from_granite_stonecutting": {
    "criteria": {
      "has_granite": "2025-05-05 15:39:16 +0000"
    },
    "done": true
  },
  "minecraft:recipes/building_blocks/polished_granite": {
    "criteria": {
      "has_granite": "2025-05-05 15:39:16 +0000"
    },
    "done": true
  },
  "minecraft:recipes/building_blocks/polished_granite_stairs_from_granite_stonecutting": {
    "criteria": {
      "has_granite": "2025-05-05 15:39:16 +0000"
    },
    "done": true
  },
  "vampirism:recipes/misc/vampire/blood_bottle_to_glass": {
    "criteria": {
      "has_blood_bottle": "2025-05-05 15:40:02 +0000"
    },
    "done": true
  },
  "vampirism:main/ancient_knowledge": {
    "criteria": {
      "blood_container": "2025-05-05 15:40:02 +0000"
    },
    "done": true
  },
  "vampirism:recipes/combat/leather_from_obi_belt": {
    "criteria": {
      "has_obi_belt": "2025-05-05 15:40:02 +0000"
    },
    "done": true
  },
  "vampirism:recipes/misc/gold_nugget_from_accessory_blasting": {
    "criteria": {
      "has_ring": "2025-05-05 15:40:15 +0000"
    },
    "done": true
  },
  "vampirism:recipes/misc/gold_nugget_from_accessory_smelting": {
    "criteria": {
      "has_ring": "2025-05-05 15:40:15 +0000"
    },
    "done": true
  },
  "vampirism:recipes/combat/vampire/heart_seeker_enhanced_repair": {
    "criteria": {
      "has_heart_seeker": "2025-05-05 15:40:53 +0000"
    },
    "done": true
  },
  "travelersbackpack:recipes/misc/standard_smithing": {
    "criteria": {
      "has_standard": "2025-05-05 15:41:56 +0000"
    },
    "done": true
  },
  "minecraft:recipes/building_blocks/andesite_stairs": {
    "criteria": {
      "has_andesite": "2025-05-05 15:44:35 +0000"
    },
    "done": true
  },
  "minecraft:recipes/decorations/andesite_wall_from_andesite_stonecutting": {
    "criteria": {
      "has_andesite": "2025-05-05 15:44:35 +0000"
    },
    "done": true
  },
  "minecraft:recipes/building_blocks/polished_andesite_slab_from_andesite_stonecutting": {
    "criteria": {
      "has_andesite": "2025-05-05 15:44:35 +0000"
    },
    "done": true
  },
  "minecraft:recipes/building_blocks/andesite_slab_from_andesite_stonecutting": {
    "criteria": {
      "has_andesite": "2025-05-05 15:44:35 +0000"
    },
    "done": true
  },
  "minecraft:recipes/building_blocks/andesite_stairs_from_andesite_stonecutting": {
    "criteria": {
      "has_andesite": "2025-05-05 15:44:35 +0000"
    },
    "done": true
  },
  "minecraft:recipes/building_blocks/polished_andesite_from_andesite_stonecutting": {
    "criteria": {
      "has_andesite": "2025-05-05 15:44:35 +0000"
    },
    "done": true
  },
  "minecraft:recipes/building_blocks/polished_andesite": {
    "criteria": {
      "has_andesite": "2025-05-05 15:44:35 +0000"
    },
    "done": true
  },
  "minecraft:recipes/decorations/andesite_wall": {
    "criteria": {
      "has_andesite": "2025-05-05 15:44:35 +0000"
    },
    "done": true
  },
  "minecraft:recipes/building_blocks/andesite_slab": {
    "criteria": {
      "has_andesite": "2025-05-05 15:44:35 +0000"
    },
    "done": true
  },
  "minecraft:recipes/building_blocks/polished_andesite_stairs_from_andesite_stonecutting": {
    "criteria": {
      "has_andesite": "2025-05-05 15:44:35 +0000"
    },
    "done": true
  },
  "minecraft:recipes/redstone/redstone_torch": {
    "criteria": {
      "has_redstone": "2025-05-05 15:45:54 +0000"
    },
    "done": true
  },
  "minecraft:recipes/tools/clock": {
    "criteria": {
      "has_redstone": "2025-05-05 15:45:54 +0000"
    },
    "done": true
  },
  "minecraft:recipes/redstone/note_block": {
    "criteria": {
      "has_redstone": "2025-05-05 15:45:54 +0000"
    },
    "done": true
  },
  "minecraft:recipes/redstone/target": {
    "criteria": {
      "has_redstone": "2025-05-05 15:45:54 +0000"
    },
    "done": true
  },
  "minecraft:recipes/tools/compass": {
    "criteria": {
      "has_redstone": "2025-05-05 15:45:54 +0000"
    },
    "done": true
  },
  "travelersbackpack:recipes/misc/redstone": {
    "criteria": {
      "has_redstone": "2025-05-05 15:45:54 +0000"
    },
    "done": true
  },
  "werewolves:recipes/misc/wolfsbane_finder": {
    "criteria": {
      "has_redstone": "2025-05-05 15:45:54 +0000"
    },
    "done": true
  },
  "minecraft:recipes/redstone/dropper": {
    "criteria": {
      "has_redstone": "2025-05-05 15:45:54 +0000"
    },
    "done": true
  },
  "minecraft:recipes/redstone/redstone_block": {
    "criteria": {
      "has_redstone": "2025-05-05 15:45:54 +0000"
    },
    "done": true
  },
  "minecraft:recipes/redstone/piston": {
    "criteria": {
      "has_redstone": "2025-05-05 15:45:54 +0000"
    },
    "done": true
  },
  "minecraft:recipes/misc/gold_ingot_from_blasting_raw_gold": {
    "criteria": {
      "has_raw_gold": "2025-05-05 15:46:21 +0000"
    },
    "done": true
  },
  "minecraft:recipes/misc/gold_ingot_from_smelting_raw_gold": {
    "criteria": {
      "has_raw_gold": "2025-05-05 15:46:21 +0000"
    },
    "done": true
  },
  "minecraft:recipes/building_blocks/raw_gold_block": {
    "criteria": {
      "has_raw_gold": "2025-05-05 15:46:21 +0000"
    },
    "done": true
  },
  "minecraft:story/deflect_arrow": {
    "criteria": {
      "deflected_projectile": "2025-05-05 15:46:45 +0000"
    },
    "done": true
  },
  "vampirism:recipes/combat/hunter/crossbow_arrow_from_vanilla": {
    "criteria": {
      "has_arrow": "2025-05-05 15:46:59 +0000"
    },
    "done": true
  },
  "travelersbackpack:recipes/misc/skeleton": {
    "criteria": {
      "has_arrow": "2025-05-05 15:46:59 +0000"
    },
    "done": true
  },
  "minecraft:recipes/building_blocks/polished_deepslate": {
    "criteria": {
      "has_cobbled_deepslate": "2025-05-05 15:47:34 +0000"
    },
    "done": true
  },
  "minecraft:recipes/building_blocks/deepslate_tile_stairs_from_cobbled_deepslate_stonecutting": {
    "criteria": {
      "has_cobbled_deepslate": "2025-05-05 15:47:34 +0000"
    },
    "done": true
  },
  "minecraft:recipes/building_blocks/deepslate_brick_stairs_from_cobbled_deepslate_stonecutting": {
    "criteria": {
      "has_cobbled_deepslate": "2025-05-05 15:47:34 +0000"
    },
    "done": true
  },
  "minecraft:recipes/building_blocks/chiseled_deepslate_from_cobbled_deepslate_stonecutting": {
    "criteria": {
      "has_cobbled_deepslate": "2025-05-05 15:47:34 +0000"
    },
    "done": true
  },
  "minecraft:recipes/building_blocks/cobbled_deepslate_slab": {
    "criteria": {
      "has_cobbled_deepslate": "2025-05-05 15:47:34 +0000"
    },
    "done": true
  },
  "minecraft:recipes/decorations/cobbled_deepslate_wall_from_cobbled_deepslate_stonecutting": {
    "criteria": {
      "has_cobbled_deepslate": "2025-05-05 15:47:34 +0000"
    },
    "done": true
  },
  "minecraft:recipes/decorations/cobbled_deepslate_wall": {
    "criteria": {
      "has_cobbled_deepslate": "2025-05-05 15:47:34 +0000"
    },
    "done": true
  },
  "minecraft:recipes/decorations/polished_deepslate_wall_from_cobbled_deepslate_stonecutting": {
    "criteria": {
      "has_cobbled_deepslate": "2025-05-05 15:47:34 +0000"
    },
    "done": true
  },
  "minecraft:recipes/building_blocks/cobbled_deepslate_stairs_from_cobbled_deepslate_stonecutting": {
    "criteria": {
      "has_cobbled_deepslate": "2025-05-05 15:47:34 +0000"
    },
    "done": true
  },
  "minecraft:recipes/building_blocks/deepslate": {
    "criteria": {
      "has_cobbled_deepslate": "2025-05-05 15:47:34 +0000"
    },
    "done": true
  },
  "minecraft:recipes/building_blocks/polished_deepslate_stairs_from_cobbled_deepslate_stonecutting": {
    "criteria": {
      "has_cobbled_deepslate": "2025-05-05 15:47:34 +0000"
    },
    "done": true
  },
  "minecraft:recipes/decorations/deepslate_brick_wall_from_cobbled_deepslate_stonecutting": {
    "criteria": {
      "has_cobbled_deepslate": "2025-05-05 15:47:34 +0000"
    },
    "done": true
  },
  "minecraft:recipes/building_blocks/polished_deepslate_from_cobbled_deepslate_stonecutting": {
    "criteria": {
      "has_cobbled_deepslate": "2025-05-05 15:47:34 +0000"
    },
    "done": true
  },
  "minecraft:recipes/building_blocks/polished_deepslate_slab_from_cobbled_deepslate_stonecutting": {
    "criteria": {
      "has_cobbled_deepslate": "2025-05-05 15:47:34 +0000"
    },
    "done": true
  },
  "minecraft:recipes/building_blocks/deepslate_brick_slab_from_cobbled_deepslate_stonecutting": {
    "criteria": {
      "has_cobbled_deepslate": "2025-05-05 15:47:34 +0000"
    },
    "done": true
  },
  "minecraft:recipes/building_blocks/cobbled_deepslate_slab_from_cobbled_deepslate_stonecutting": {
    "criteria": {
      "has_cobbled_deepslate": "2025-05-05 15:47:34 +0000"
    },
    "done": true
  },
  "minecraft:recipes/building_blocks/deepslate_tile_slab_from_cobbled_deepslate_stonecutting": {
    "criteria": {
      "has_cobbled_deepslate": "2025-05-05 15:47:34 +0000"
    },
    "done": true
  },
  "minecraft:recipes/building_blocks/cobbled_deepslate_stairs": {
    "criteria": {
      "has_cobbled_deepslate": "2025-05-05 15:47:34 +0000"
    },
    "done": true
  },
  "minecraft:recipes/decorations/deepslate_tile_wall_from_cobbled_deepslate_stonecutting": {
    "criteria": {
      "has_cobbled_deepslate": "2025-05-05 15:47:34 +0000"
    },
    "done": true
  },
  "minecraft:recipes/building_blocks/deepslate_bricks_from_cobbled_deepslate_stonecutting": {
    "criteria": {
      "has_cobbled_deepslate": "2025-05-05 15:47:34 +0000"
    },
    "done": true
  },
  "minecraft:recipes/building_blocks/deepslate_tiles_from_cobbled_deepslate_stonecutting": {
    "criteria": {
      "has_cobbled_deepslate": "2025-05-05 15:47:34 +0000"
    },
    "done": true
  },
  "minecraft:recipes/misc/bone_meal": {
    "criteria": {
      "has_bone": "2025-05-05 15:49:13 +0000"
    },
    "done": true
  },
  "travelersbackpack:recipes/misc/wolf": {
    "criteria": {
      "has_bone": "2025-05-05 15:49:13 +0000"
    },
    "done": true
  },
  "minecraft:recipes/misc/blue_dye": {
    "criteria": {
      "has_lapis_lazuli": "2025-05-05 15:49:41 +0000"
    },
    "done": true
  },
  "minecraft:recipes/building_blocks/lapis_block": {
    "criteria": {
      "has_lapis_lazuli": "2025-05-05 15:49:41 +0000"
    },
    "done": true
  },
  "travelersbackpack:recipes/misc/lapis": {
    "criteria": {
      "has_lapis_lazuli": "2025-05-05 15:49:41 +0000"
    },
    "done": true
  },
  "vampirism:recipes/decorations/vampire/fog_diffuser": {
    "criteria": {
      "has_diamond": "2025-05-05 15:53:17 +0000"
    },
    "done": true
  },
  "minecraft:recipes/combat/diamond_leggings": {
    "criteria": {
      "has_diamond": "2025-05-05 15:53:17 +0000"
    },
    "done": true
  },
  "minecraft:recipes/combat/diamond_sword": {
    "criteria": {
      "has_diamond": "2025-05-05 15:53:17 +0000"
    },
    "done": true
  },
  "minecraft:recipes/decorations/jukebox": {
    "criteria": {
      "has_diamond": "2025-05-05 15:53:17 +0000"
    },
    "done": true
  },
  "minecraft:recipes/combat/diamond_chestplate": {
    "criteria": {
      "has_diamond": "2025-05-05 15:53:17 +0000"
    },
    "done": true
  },
  "minecraft:recipes/decorations/wolfsbane_diffuser_improved": {
    "criteria": {
      "has_diamond": "2025-05-05 15:53:17 +0000"
    },
    "done": true
  },
  "minecraft:recipes/tools/diamond_pickaxe": {
    "criteria": {
      "has_diamond": "2025-05-05 15:53:17 +0000"
    },
    "done": true
  },
  "minecraft:recipes/tools/diamond_hoe": {
    "criteria": {
      "has_diamond": "2025-05-05 15:53:17 +0000"
    },
    "done": true
  },
  "minecraft:recipes/tools/diamond_shovel": {
    "criteria": {
      "has_diamond": "2025-05-05 15:53:17 +0000"
    },
    "done": true
  },
  "minecraft:recipes/combat/diamond_boots": {
    "criteria": {
      "has_diamond": "2025-05-05 15:53:17 +0000"
    },
    "done": true
  },
  "travelersbackpack:recipes/misc/diamond_tier_upgrade": {
    "criteria": {
      "has_diamond": "2025-05-05 15:53:17 +0000"
    },
    "done": true
  },
  "vampirism:recipes/decorations/hunter/garlic_diffuser_normal": {
    "criteria": {
      "has_diamond": "2025-05-05 15:53:17 +0000"
    },
    "done": true
  },
  "minecraft:recipes/combat/diamond_helmet": {
    "criteria": {
      "has_diamond": "2025-05-05 15:53:17 +0000"
    },
    "done": true
  },
  "minecraft:recipes/decorations/wolfsbane_diffuser_normal": {
    "criteria": {
      "has_diamond": "2025-05-05 15:53:17 +0000"
    },
    "done": true
  },
  "travelersbackpack:recipes/misc/diamond": {
    "criteria": {
      "has_diamond": "2025-05-05 15:53:17 +0000"
    },
    "done": true
  },
  "minecraft:recipes/building_blocks/diamond_block": {
    "criteria": {
      "has_diamond": "2025-05-05 15:53:17 +0000"
    },
    "done": true
  },
  "minecraft:story/mine_diamond": {
    "criteria": {
      "diamond": "2025-05-05 15:53:17 +0000"
    },
    "done": true
  },
  "minecraft:recipes/tools/diamond_axe": {
    "criteria": {
      "has_diamond": "2025-05-05 15:53:17 +0000"
    },
    "done": true
  },
  "travelersbackpack:recipes/misc/iron_smithing": {
    "criteria": {
      "has_iron": "2025-05-05 15:55:18 +0000"
    },
    "done": true
  },
  "werewolves:recipes/alchemy_table/alchemy_table/silver_oil_2": {
    "criteria": {
      "has_silver_ingot": "2025-05-05 16:06:13 +0000"
    },
    "done": true
  },
  "werewolves:recipes/alchemy_table/alchemy_table/silver_oil_1": {
    "criteria": {
      "has_silver_ingot": "2025-05-05 16:06:13 +0000"
    },
    "done": true
  },
  "werewolves:recipes/combat/silver_leggings": {
    "criteria": {
      "has_silver_ingot": "2025-05-05 16:06:13 +0000"
    },
    "done": true
  },
  "werewolves:recipes/combat/silver_chestplate": {
    "criteria": {
      "has_silver_ingot": "2025-05-05 16:06:13 +0000"
    },
    "done": true
  },
  "werewolves:recipes/combat/silver_boots": {
    "criteria": {
      "has_silver_ingot": "2025-05-05 16:06:13 +0000"
    },
    "done": true
  },
  "werewolves:recipes/combat/silver_helmet": {
    "criteria": {
      "has_silver_ingot": "2025-05-05 16:06:13 +0000"
    },
    "done": true
  },
  "minecraft:recipes/misc/silver_nugget": {
    "criteria": {
      "has_silver_ingot": "2025-05-05 16:06:13 +0000"
    },
    "done": true
  },
  "minecraft:recipes/misc/silver_block": {
    "criteria": {
      "has_silver_ingot": "2025-05-05 16:06:13 +0000"
    },
    "done": true
  },
  "minecraft:recipes/brewing/cauldron": {
    "criteria": {
      "has_water_bucket": "2025-05-06 02:37:16 +0000"
    },
    "done": true
  },
  "minecraft:recipes/decorations/polished_blackstone_brick_wall_from_blackstone_stonecutting": {
    "criteria": {
      "has_blackstone": "2025-05-06 02:41:05 +0000"
    },
    "done": true
  },
  "minecraft:recipes/decorations/blackstone_wall": {
    "criteria": {
      "has_blackstone": "2025-05-06 02:41:05 +0000"
    },
    "done": true
  },
  "minecraft:recipes/building_blocks/polished_blackstone_brick_stairs_from_blackstone_stonecutting": {
    "criteria": {
      "has_blackstone": "2025-05-06 02:41:05 +0000"
    },
    "done": true
  },
  "minecraft:recipes/building_blocks/polished_blackstone_bricks_from_blackstone_stonecutting": {
    "criteria": {
      "has_blackstone": "2025-05-06 02:41:05 +0000"
    },
    "done": true
  },
  "minecraft:recipes/building_blocks/polished_blackstone_stairs_from_blackstone_stonecutting": {
    "criteria": {
      "has_blackstone": "2025-05-06 02:41:05 +0000"
    },
    "done": true
  },
  "minecraft:recipes/decorations/polished_blackstone_wall_from_blackstone_stonecutting": {
    "criteria": {
      "has_blackstone": "2025-05-06 02:41:05 +0000"
    },
    "done": true
  },
  "minecraft:recipes/building_blocks/chiseled_polished_blackstone_from_blackstone_stonecutting": {
    "criteria": {
      "has_blackstone": "2025-05-06 02:41:05 +0000"
    },
    "done": true
  },
  "minecraft:recipes/building_blocks/blackstone_stairs": {
    "criteria": {
      "has_blackstone": "2025-05-06 02:41:05 +0000"
    },
    "done": true
  },
  "minecraft:recipes/building_blocks/blackstone_slab_from_blackstone_stonecutting": {
    "criteria": {
      "has_blackstone": "2025-05-06 02:41:05 +0000"
    },
    "done": true
  },
  "minecraft:recipes/building_blocks/polished_blackstone_slab_from_blackstone_stonecutting": {
    "criteria": {
      "has_blackstone": "2025-05-06 02:41:05 +0000"
    },
    "done": true
  },
  "minecraft:recipes/building_blocks/polished_blackstone": {
    "criteria": {
      "has_blackstone": "2025-05-06 02:41:05 +0000"
    },
    "done": true
  },
  "minecraft:recipes/building_blocks/blackstone_slab": {
    "criteria": {
      "has_blackstone": "2025-05-06 02:41:05 +0000"
    },
    "done": true
  },
  "minecraft:recipes/building_blocks/polished_blackstone_brick_slab_from_blackstone_stonecutting": {
    "criteria": {
      "has_blackstone": "2025-05-06 02:41:05 +0000"
    },
    "done": true
  },
  "minecraft:recipes/building_blocks/polished_blackstone_from_blackstone_stonecutting": {
    "criteria": {
      "has_blackstone": "2025-05-06 02:41:05 +0000"
    },
    "done": true
  },
  "minecraft:recipes/decorations/blackstone_wall_from_blackstone_stonecutting": {
    "criteria": {
      "has_blackstone": "2025-05-06 02:41:05 +0000"
    },
    "done": true
  },
  "minecraft:recipes/building_blocks/blackstone_stairs_from_blackstone_stonecutting": {
    "criteria": {
      "has_blackstone": "2025-05-06 02:41:05 +0000"
    },
    "done": true
  },
  "minecraft:recipes/combat/bow": {
    "criteria": {
      "has_string": "2025-05-06 02:50:04 +0000"
    },
    "done": true
  },
  "minecraft:recipes/tools/fishing_rod": {
    "criteria": {
      "has_string": "2025-05-06 02:50:04 +0000"
    },
    "done": true
  },
  "minecraft:recipes/redstone/tripwire_hook": {
    "criteria": {
      "has_string": "2025-05-06 02:50:04 +0000"
    },
    "done": true
  },
  "travelersbackpack:recipes/misc/spider": {
    "criteria": {
      "has_string": "2025-05-06 02:50:04 +0000"
    },
    "done": true
  },
  "minecraft:recipes/decorations/candle": {
    "criteria": {
      "has_string": "2025-05-06 02:50:04 +0000"
    },
    "done": true
  },
  "vampirism:recipes/decorations/vampire/chandelier": {
    "criteria": {
      "has_string": "2025-05-06 02:50:04 +0000"
    },
    "done": true
  },
  "minecraft:recipes/building_blocks/white_wool_from_string": {
    "criteria": {
      "has_string": "2025-05-06 02:50:04 +0000"
    },
    "done": true
  },
  "minecraft:recipes/decorations/loom": {
    "criteria": {
      "has_string": "2025-05-06 02:50:04 +0000"
    },
    "done": true
  },
  "endrem:main/root": {
    "criteria": {
      "lost_eye": "2025-05-06 02:51:09 +0000"
    },
    "done": true
  },
  "endrem:main/lost_eye": {
    "criteria": {
      "lost_eye": "2025-05-06 02:51:09 +0000"
    },
    "done": true
  },
  "minecraft:recipes/misc/bone": {
    "criteria": {
      "has_broken_bone": "2025-05-06 02:51:34 +0000"
    },
    "done": true
  },
  "vampirism:recipes/combat/vampire/heart_striker_enhanced_repair": {
    "criteria": {
      "has_heart_striker": "2025-05-06 02:52:15 +0000"
    },
    "done": true
  },
  "minecraft:recipes/transportation/activator_rail": {
    "criteria": {
      "has_rail": "2025-05-06 02:53:14 +0000"
    },
    "done": true
  },
  "minecraft:recipes/transportation/detector_rail": {
    "criteria": {
      "has_rail": "2025-05-06 02:53:14 +0000"
    },
    "done": true
  },
  "minecraft:recipes/transportation/powered_rail": {
    "criteria": {
      "has_rail": "2025-05-06 02:53:14 +0000"
    },
    "done": true
  },
  "minecraft:recipes/decorations/oak_sign": {
    "criteria": {
      "has_planks": "2025-05-06 02:55:17 +0000"
    },
    "done": true
  },
  "minecraft:recipes/redstone/oak_trapdoor": {
    "criteria": {
      "has_planks": "2025-05-06 02:55:17 +0000"
    },
    "done": true
  },
  "minecraft:recipes/building_blocks/oak_stairs": {
    "criteria": {
      "has_planks": "2025-05-06 02:55:17 +0000"
    },
    "done": true
  },
  "minecraft:recipes/decorations/oak_fence": {
    "criteria": {
      "has_planks": "2025-05-06 02:55:17 +0000"
    },
    "done": true
  },
  "minecraft:recipes/redstone/oak_button": {
    "criteria": {
      "has_planks": "2025-05-06 02:55:17 +0000"
    },
    "done": true
  },
  "minecraft:recipes/building_blocks/oak_slab": {
    "criteria": {
      "has_planks": "2025-05-06 02:55:17 +0000"
    },
    "done": true
  },
  "minecraft:recipes/redstone/oak_fence_gate": {
    "criteria": {
      "has_planks": "2025-05-06 02:55:17 +0000"
    },
    "done": true
  },
  "minecraft:recipes/redstone/oak_pressure_plate": {
    "criteria": {
      "has_planks": "2025-05-06 02:55:17 +0000"
    },
    "done": true
  },
  "minecraft:recipes/redstone/oak_door": {
    "criteria": {
      "has_planks": "2025-05-06 02:55:17 +0000"
    },
    "done": true
  },
  "minecraft:recipes/combat/arrow": {
    "criteria": {
      "has_feather": "2025-05-06 14:39:41 +0000"
    },
    "done": true
  },
  "minecraft:recipes/building_blocks/emerald_block": {
    "criteria": {
      "has_emerald": "2025-05-06 14:32:40 +0000"
    },
    "done": true
  },
  "travelersbackpack:recipes/misc/emerald": {
    "criteria": {
      "has_emerald": "2025-05-06 14:32:40 +0000"
    },
    "done": true
  },
  "travelersbackpack:recipes/misc/chicken": {
    "criteria": {
      "has_feather": "2025-05-06 14:39:41 +0000"
    },
    "done": true
  },
  "travelersbackpack:recipes/misc/standard_no_tanks": {
    "criteria": {
      "has_chest": "2025-05-06 15:04:22 +0000"
    },
    "done": true
  },
  "travelersbackpack:recipes/misc/standard": {
    "criteria": {
      "has_chest": "2025-05-06 15:04:22 +0000"
    },
    "done": true
  },
  "minecraft:recipes/building_blocks/acacia_wood": {
    "criteria": {
      "has_log": "2025-05-06 15:17:21 +0000"
    },
    "done": true
  },
  "minecraft:recipes/building_blocks/acacia_planks": {
    "criteria": {
      "has_log": "2025-05-06 15:17:21 +0000"
    },
    "done": true
  },
  "DataVersion": 3465
}